esiclient/__init__.py
esiclient/plugin.py
esiclient/utils.py
esiclient/tests/__init__.py
esiclient/tests/functional/README.md
esiclient/tests/functional/__init__.py
esiclient/tests/functional/base.py
esiclient/tests/functional/test.conf.sample
esiclient/tests/functional/utils.py
esiclient/tests/functional/v1/__init__.py
esiclient/tests/functional/v1/test_image.py
esiclient/tests/functional/v1/test_metalsmith.py
esiclient/tests/functional/v1/test_network.py
esiclient/tests/functional/v1/test_node.py
esiclient/tests/functional/v1/test_node_network.py
esiclient/tests/functional/v1/test_node_volume.py
esiclient/tests/functional/v1/test_trunk.py
esiclient/tests/functional/v1/test_volume.py
esiclient/tests/unit/__init__.py
esiclient/tests/unit/base.py
esiclient/tests/unit/test_utils.py
esiclient/tests/unit/utils.py
esiclient/tests/unit/v1/__init__.py
esiclient/tests/unit/v1/test_node_console.py
esiclient/tests/unit/v1/test_node_network.py
esiclient/tests/unit/v1/test_node_volume.py
esiclient/tests/unit/v1/test_port_forwarding.py
esiclient/tests/unit/v1/test_switch.py
esiclient/tests/unit/v1/test_trunk.py
esiclient/tests/unit/v1/cluster/__init__.py
esiclient/tests/unit/v1/cluster/test_cluster.py
esiclient/tests/unit/v1/cluster/test_openshift.py
esiclient/tests/unit/v1/cluster/test_utils.py
esiclient/tests/unit/v1/mdc/__init__.py
esiclient/tests/unit/v1/mdc/test_mdc_node_baremetal.py
esiclient/v1/__init__.py
esiclient/v1/node_console.py
esiclient/v1/node_network.py
esiclient/v1/node_volume.py
esiclient/v1/port_forwarding.py
esiclient/v1/switch.py
esiclient/v1/trunk.py
esiclient/v1/cluster/__init__.py
esiclient/v1/cluster/cluster.py
esiclient/v1/cluster/openshift.py
esiclient/v1/cluster/utils.py
esiclient/v1/mdc/__init__.py
esiclient/v1/mdc/mdc_node_baremetal.py
python_esiclient-1.3.0.dist-info/licenses/AUTHORS
python_esiclient-1.3.0.dist-info/licenses/LICENSE
python_esiclient-1.3.0.dist-info/METADATA
python_esiclient-1.3.0.dist-info/WHEEL
python_esiclient-1.3.0.dist-info/entry_points.txt
python_esiclient-1.3.0.dist-info/pbr.json
python_esiclient-1.3.0.dist-info/top_level.txt
python_esiclient-1.3.0.dist-info/RECORD
