Metadata-Version: 2.4
Name: python-esiclient
Version: 1.3.0
Summary: ESI client
Author: ESI
Author-email: esi@lists.massopen.cloud
License: Apache License, Version 2.0
Classifier: Environment :: Console
Classifier: Environment :: OpenStack
Classifier: Intended Audience :: Developers
Classifier: Intended Audience :: Information Technology
Classifier: Intended Audience :: System Administrators
Classifier: License :: OSI Approved :: Apache Software License
Classifier: Operating System :: OS Independent
Classifier: Programming Language :: Python
Classifier: Programming Language :: Python :: Implementation :: CPython
Classifier: Programming Language :: Python :: 3 :: Only
Classifier: Programming Language :: Python :: 3
Classifier: Programming Language :: Python :: 3.6
Classifier: Programming Language :: Python :: 3.7
Requires-Python: >=3.6
License-File: LICENSE
License-File: AUTHORS
Requires-Dist: pbr!=2.1.0,>=2.0.0
Requires-Dist: Babel!=2.4.0,>=2.3.4
Requires-Dist: esisdk>=1.4
Requires-Dist: metalsmith>=2.0.0
Requires-Dist: openstacksdk
Requires-Dist: oslo.utils>=4.5.0
Requires-Dist: pbr!=2.1.0,>=2.0.0
Requires-Dist: passlib>=1.7.0
Requires-Dist: psutil>=3.2.2
Requires-Dist: python-ironicclient!=2.5.2,!=2.7.1,!=3.0.0,>=2.3.0
Requires-Dist: python-novaclient==17.4.0
Requires-Dist: python-openstackclient>=5.2.0
Requires-Dist: simplejson>=3.5.1
Requires-Dist: six>=1.10.0
Requires-Dist: osc-lib>=1.8.0
Requires-Dist: websocket-client>=0.44.0
Requires-Dist: ansible-runner>=1.4.4
Dynamic: author
Dynamic: author-email
Dynamic: classifier
Dynamic: description
Dynamic: description-content-type
Dynamic: license
Dynamic: license-file
Dynamic: requires-dist
Dynamic: requires-python
Dynamic: summary
